aiorotation/__init__.py
aiorotation/limit.py
aiorotation/rotator.py
aiorotation/token.py
aiorotation-0.1.0.dist-info/licenses/LICENSE
aiorotation-0.1.0.dist-info/METADATA
aiorotation-0.1.0.dist-info/WHEEL
aiorotation-0.1.0.dist-info/top_level.txt
aiorotation-0.1.0.dist-info/RECORD
