Metadata-Version: 2.4
Name: aiorotation
Version: 0.1.0
Summary: Asynchronous library for easy requests to APIs with any rate limits, with support for token rotation.
Author: Creeper Hack
License: MIT
Project-URL: Homepage, https://github.com/creehk/aiorotation
Requires-Python: >=3.8
License-File: LICENSE
Dynamic: license-file
